biosimulators_pyneuroml/__init__.py
biosimulators_pyneuroml/_version.py
biosimulators_pyneuroml/core.py
biosimulators_pyneuroml/data_model.py
biosimulators_pyneuroml/utils.py
biosimulators_pyneuroml/api/__init__.py
biosimulators_pyneuroml/api/brian2.py
biosimulators_pyneuroml/api/netpyne.py
biosimulators_pyneuroml/api/neuron.py
biosimulators_pyneuroml/api/pyneuroml.py
biosimulators_pyneuroml/cli/__init__.py
biosimulators_pyneuroml/cli/brian2.py
biosimulators_pyneuroml/cli/netpyne.py
biosimulators_pyneuroml/cli/neuron.py
biosimulators_pyneuroml/cli/pyneuroml.py
biosimulators_pyneuroml-0.0.16.dist-info/LICENSE
biosimulators_pyneuroml-0.0.16.dist-info/METADATA
biosimulators_pyneuroml-0.0.16.dist-info/WHEEL
biosimulators_pyneuroml-0.0.16.dist-info/entry_points.txt
biosimulators_pyneuroml-0.0.16.dist-info/top_level.txt
biosimulators_pyneuroml-0.0.16.dist-info/RECORD
