Metadata-Version: 2.1
Name: biosimulators-pyneuroml
Version: 0.0.16
Summary: BioSimulators-compliant command-line interface to the jNeuroML/pyNeuroML, NEURON, and NetPyNe simulation programs.
Home-page: https://github.com/biosimulators/Biosimulators_pyNeuroML
Download-URL: https://github.com/biosimulators/Biosimulators_pyNeuroML
Author: BioSimulators Team
Author-email: info@biosimulators.org
License: MIT
Keywords: computational neuroscience,dynamical modeling,numerical simulation,NeuroML,LEMS,SED-ML,COMBINE,OMEX
Platform: UNKNOWN
Classifier: Development Status :: 3 - Alpha
Classifier: Intended Audience :: Science/Research
Classifier: License :: OSI Approved :: MIT License
Classifier: Topic :: Scientific/Engineering :: Bio-Informatics
License-File: LICENSE
Requires-Dist: biosimulators-utils[lems,logging,neuroml] (>=0.1.147)
Requires-Dist: kisao
Requires-Dist: lxml
Requires-Dist: netpyne (<=1.0.0.2)
Requires-Dist: numpy
Requires-Dist: psutil
Requires-Dist: pyneuroml (>=0.5.20)
Provides-Extra: all
Requires-Dist: biosimulators-utils[containers] ; extra == 'all'
Requires-Dist: brian2 ; extra == 'all'
Requires-Dist: netpyne ; extra == 'all'
Requires-Dist: neuron ; extra == 'all'
Requires-Dist: parameterized ; extra == 'all'
Requires-Dist: python-dateutil ; extra == 'all'
Provides-Extra: brian2
Requires-Dist: brian2 ; extra == 'brian2'
Provides-Extra: docs
Provides-Extra: netpyne
Requires-Dist: netpyne ; extra == 'netpyne'
Requires-Dist: neuron ; extra == 'netpyne'
Provides-Extra: neuron
Requires-Dist: neuron ; extra == 'neuron'
Provides-Extra: tests
Requires-Dist: biosimulators-utils[containers] ; extra == 'tests'
Requires-Dist: parameterized ; extra == 'tests'
Requires-Dist: python-dateutil ; extra == 'tests'
